setup.cfg
setup.py
grill_maya/__init__.py
grill_maya/apiutils.py
grill_maya/names.py
grill_maya.egg-info/PKG-INFO
grill_maya.egg-info/SOURCES.txt
grill_maya.egg-info/dependency_links.txt
grill_maya.egg-info/top_level.txt
grill_maya/animation/__init__.py
grill_maya/animation/controller.py
grill_maya/exc_handler/__init__.py
grill_maya/exc_handler/controller.py