Metadata-Version: 1.1
Name: grill-maya
Version: 0.1.0.0
Summary: Maya tools expanding the grill framework.
Home-page: https://github.com/chrizzFTD/grill-maya
Author: Christian Lopez Barron
Author-email: christianlb.vfx@outlook.com
License: UNKNOWN
Download-URL: https://github.com/chrizzFTD/grill-maya/releases/tag/0.1.0.0
Platform: UNKNOWN
